AMTIUSBDeviceWrapper/AMTIUSBDevice.py
AMTIUSBDeviceWrapper/__init__.py
amtiusbdevicewrapper-1.1.2.dist-info/METADATA
amtiusbdevicewrapper-1.1.2.dist-info/WHEEL
amtiusbdevicewrapper-1.1.2.dist-info/licenses/LICENSE
amtiusbdevicewrapper-1.1.2.dist-info/RECORD
