Metadata-Version: 2.1
Name: AMTIUSBDeviceWrapper
Version: 1.1.2
Summary: Wrapper for AMTI USB Device library. Currently only supported on Windows Systems for 32 and 64 bit versions of the SDK. Use 64 bit dll if running 64 bit python interpreter and vice versa with 32 bit dll.
Project-URL: Homepage, https://github.com/Lenz-Lab/AMTIUSBDeviceWrapper
Author-email: Jordy Larrea Rodriguez <Jordy.larrearodriguez@gmail.com>
License-File: LICENSE
Classifier: License :: CC0 1.0 Universal (CC0 1.0) Public Domain Dedication
Classifier: Operating System :: Microsoft :: Windows :: Windows 10
Classifier: Programming Language :: Python :: 3
Requires-Python: >=3.7
